strangedateutils/__init__.py
strangedateutils-0.2.dist-info/DESCRIPTION.rst
strangedateutils-0.2.dist-info/METADATA
strangedateutils-0.2.dist-info/RECORD
strangedateutils-0.2.dist-info/WHEEL
strangedateutils-0.2.dist-info/metadata.json
strangedateutils-0.2.dist-info/top_level.txt
