Metadata-Version: 2.0
Name: strangedateutils
Version: 0.2
Summary: Some date methods have been used in my daily work. It's not common but may help someone.
Home-page: https://github.com/huadi/StrangeDateUtils
Author: huadi
Author-email: huadi223@gmail.com
License: MIT
Platform: UNKNOWN
